ufs/__init__.py
ufs/base.py
ufs/exceptions.py
ufs/posix/__init__.py
ufs/posix/posix_common.py
ufs/posix/posix_directory.py
ufs/posix/posix_directory_prefix.py
ufs/posix/posix_file.py
ufs/posix/posix_filesystem.py
ufs/s3/__init__.py
ufs/s3/s3_common.py
ufs/s3/s3_directory.py
ufs/s3/s3_directory_prefix.py
ufs/s3/s3_file.py
ufs/s3/s3_filesystem.py
ufs-0.1.0.dist-info/LICENSE
ufs-0.1.0.dist-info/METADATA
ufs-0.1.0.dist-info/WHEEL
ufs-0.1.0.dist-info/RECORD
