Metadata-Version: 2.1
Name: ufs
Version: 0.1.0
Summary: Unified File System - Object Oriented way to work seamlessly between Posix and S3 filesystems
Home-page: https://github.com/spsoni/ufs
License: MIT
Keywords: FileSystem,Posix,AWS,S3
Author: Sury Soni
Author-email: github@suryasoni.info
Requires-Python: >=3.8.1,<4.0.0
Classifier: License :: OSI Approved :: MIT License
Classifier: Programming Language :: Python :: 3
Classifier: Programming Language :: Python :: 3.9
Classifier: Programming Language :: Python :: 3.10
Classifier: Programming Language :: Python :: 3.11
Project-URL: Repository, https://github.com/spsoni/ufs
